fastmri/__init__.py
fastmri/_version.py
fastmri/coil_combine.py
fastmri/evaluate.py
fastmri/fftc.py
fastmri/losses.py
fastmri/math.py
fastmri/utils.py
fastmri/data/__init__.py
fastmri/data/mri_data.py
fastmri/data/subsample.py
fastmri/data/transforms.py
fastmri/data/volume_sampler.py
fastmri/models/__init__.py
fastmri/models/adaptive_varnet.py
fastmri/models/policy.py
fastmri/models/unet.py
fastmri/models/varnet.py
fastmri/pl_modules/__init__.py
fastmri/pl_modules/data_module.py
fastmri/pl_modules/mri_module.py
fastmri/pl_modules/unet_module.py
fastmri/pl_modules/varnet_module.py
fastmri-0.3.0.dist-info/LICENSE.md
fastmri-0.3.0.dist-info/METADATA
fastmri-0.3.0.dist-info/WHEEL
fastmri-0.3.0.dist-info/top_level.txt
fastmri-0.3.0.dist-info/RECORD
