Metadata-Version: 2.1
Name: fastmri
Version: 0.3.0
Summary: A large-scale dataset of both raw MRI measurements and clinical MRI images.
Author: Meta/NYU fastMRI Team
Author-email: fastmri@fb.com
License: MIT
Project-URL: Homepage, https://fastmri.org/
Project-URL: Source, https://github.com/facebookresearch/fastMRI
Classifier: Programming Language :: Python :: 3
Classifier: Programming Language :: Python :: 3.8
Classifier: License :: OSI Approved :: MIT License
Classifier: Operating System :: OS Independent
Classifier: Development Status :: 3 - Alpha
Classifier: Intended Audience :: Developers
Classifier: Topic :: Scientific/Engineering :: Artificial Intelligence
Classifier: Topic :: Scientific/Engineering :: Image Processing
Classifier: Topic :: Scientific/Engineering :: Medical Science Apps.
Classifier: Topic :: Scientific/Engineering :: Physics
Requires-Python: >=3.8
Provides-Extra: dev
Provides-Extra: tests
License-File: LICENSE.md
